LICENSE
README.md
setup.py
pubmedflow/__init__.py
pubmedflow/pubmedflow.py
pubmedflow/utils.py
pubmedflow.egg-info/PKG-INFO
pubmedflow.egg-info/SOURCES.txt
pubmedflow.egg-info/dependency_links.txt
pubmedflow.egg-info/requires.txt
pubmedflow.egg-info/top_level.txt