Metadata-Version: 2.1
Name: pubmedflow
Version: 0.0.2
Summary: Data Collection from pubmed made easy
Home-page: https://github.com/nfflow/pubmedflow
Author: Aditya Ura
Author-email: aadityaura@gmail.com
License: MIT License
Requires-Python: >=3.6
Provides-Extra: qa
License-File: LICENSE
